{
  "Version": 3,
  "Meta": {
    "Duration": 3.47,
    "Fps": 30.0,
    "Loop": false,
    "CurveCount": 135,
    "TotalSegmentCount": 422,
    "TotalPointCount": 1163,
    "UserDataCount": 1,
    "TotalUserDataSize": 0
  },
  "Curves": [
    {
      "Target": "Parameter",
      "Id": "ParamAngleX",
      "Segments": [
        0,
        0,
        1,
        0.044,
        0,
        0.089,
        -19,
        0.133,
        -19,
        1,
        0.278,
        -19,
        0.422,
        13.692,
        0.567,
        15,
        1,
        1.334,
        21.94,
        2.1,
        24,
        2.867,
        24,
        1,
        3,
        24,
        3.134,
        0,
        3.267,
        0,
        2,
        3.467,
        0
      ]
    },
    {
      "Target": "Parameter",
      "Id": "ParamAngleY",
      "Segments": [
        0,
        0,
        2,
        0.067,
        0,
        1,
        0.122,
        0,
        0.178,
        -19,
        0.233,
        -19,
        1,
        0.422,
        -19,
        0.611,
        23,
        0.8,
        23,
        1,
        1.089,
        23,
        1.378,
        -15,
        1.667,
        -15,
        1,
        2.078,
        -15,
        2.489,
        0,
        2.9,
        0,
        2,
        3.267,
        0,
        2,
        3.467,
        0
      ]
    },
    {
      "Target": "Parameter",
      "Id": "ParamAngleZ",
      "Segments": [
        0,
        0,
        1,
        0.056,
        0,
        0.111,
        -30,
        0.167,
        -30,
        1,
        0.4,
        -30,
        0.634,
        -20.94,
        0.867,
        0,
        1,
        1.078,
        18.946,
        1.289,
        30,
        1.5,
        30,
        1,
        1.9,
        30,
        2.3,
        -23.702,
        2.7,
        -23.702,
        1,
        2.833,
        -23.702,
        2.967,
        7.328,
        3.1,
        7.328,
        1,
        3.222,
        7.328,
        3.345,
        1.564,
        3.467,
        0
      ]
    },
    {
      "Target": "Parameter",
      "Id": "ParamBodyAngleX",
      "Segments": [
        0,
        0,
        1,
        0.067,
        0,
        0.133,
        -8,
        0.2,
        -8,
        1,
        0.411,
        -8,
        0.622,
        18,
        0.833,
        18,
        1,
        1.133,
        18,
        1.433,
        7,
        1.733,
        7,
        1,
        2.033,
        7,
        2.333,
        10,
        2.633,
        10,
        1,
        2.811,
        10,
        2.989,
        0,
        3.167,
        0,
        2,
        3.467,
        0
      ]
    },
    {
      "Target": "Parameter",
      "Id": "ParamBodyAngleZ",
      "Segments": [
        0,
        0,
        1,
        0.067,
        0,
        0.133,
        -2,
        0.2,
        -2,
        1,
        0.411,
        -2,
        0.622,
        10,
        0.833,
        10,
        1,
        1.244,
        10,
        1.656,
        -6.053,
        2.067,
        -8.124,
        1,
        2.434,
        -8.124,
        2.8,
        0,
        3.167,
        0,
        2,
        3.467,
        0
      ]
    },
    {
      "Target": "Parameter",
      "Id": "Param3Body",
      "Segments": [
        0,
        0,
        1,
        0.078,
        0,
        0.155,
        -30,
        0.233,
        -30,
        1,
        0.433,
        -30,
        0.633,
        30,
        0.833,
        30,
        1,
        1.144,
        30,
        1.456,
        4.615,
        1.767,
        3,
        1,
        2.334,
        0.059,
        2.9,
        0,
        3.467,
        0
      ]
    },
    {
      "Target": "Parameter",
      "Id": "ParamBreath",
      "Segments": [
        0,
        0,
        1,
        0.433,
        0,
        0.867,
        1,
        1.3,
        1,
        1,
        2.022,
        1,
        2.745,
        0,
        3.467,
        0
      ]
    },
    {
      "Target": "Parameter",
      "Id": "Param2bodyX",
      "Segments": [
        0,
        0,
        1,
        0.256,
        0,
        0.511,
        16,
        0.767,
        16,
        1,
        1.1,
        16,
        1.434,
        13.95,
        1.767,
        10,
        1,
        2.334,
        3.285,
        2.9,
        0,
        3.467,
        0
      ]
    },
    {
      "Target": "Parameter",
      "Id": "Param2bodyY",
      "Segments": [
        0,
        0,
        1,
        0.056,
        0,
        0.111,
        -14,
        0.167,
        -14,
        1,
        0.367,
        -14,
        0.567,
        12,
        0.767,
        12,
        1,
        1.1,
        12,
        1.434,
        -9,
        1.767,
        -9,
        1,
        2.034,
        -9,
        2.3,
        13,
        2.567,
        13,
        1,
        2.867,
        13,
        3.167,
        0,
        3.467,
        0
      ]
    },
    {
      "Target": "Parameter",
      "Id": "Param3STDXZ",
      "Segments": [
        0,
        0,
        1,
        0.278,
        0,
        0.555,
        6,
        0.833,
        6,
        1,
        1.366,
        6,
        1.9,
        0,
        2.433,
        0,
        2,
        3.467,
        0
      ]
    },
    {
      "Target": "Parameter",
      "Id": "Param2shipY",
      "Segments": [
        0,
        0,
        1,
        0.544,
        0,
        1.089,
        -18,
        1.633,
        -18,
        1,
        2.244,
        -18,
        2.856,
        0,
        3.467,
        0
      ]
    },
    {
      "Target": "Parameter",
      "Id": "Param3ship2X",
      "Segments": [
        0,
        0,
        1,
        0.189,
        0,
        0.378,
        16,
        0.567,
        16,
        1,
        0.778,
        16,
        0.989,
        14.914,
        1.2,
        13,
        1,
        1.356,
        11.589,
        1.511,
        10.504,
        1.667,
        9,
        1,
        2.267,
        3.2,
        2.867,
        0,
        3.467,
        0
      ]
    },
    {
      "Target": "Parameter",
      "Id": "Paramship2Y",
      "Segments": [
        0,
        0,
        1,
        0.189,
        0,
        0.378,
        -21,
        0.567,
        -21,
        1,
        0.778,
        -21,
        0.989,
        4,
        1.2,
        4,
        1,
        1.356,
        4,
        1.511,
        1.213,
        1.667,
        1,
        1,
        2.267,
        0.18,
        2.867,
        0,
        3.467,
        0
      ]
    },
    {
      "Target": "Parameter",
      "Id": "Param2ship7",
      "Segments": [
        0,
        0,
        2,
        0.367,
        0,
        1,
        0.5,
        0,
        0.634,
        -17,
        0.767,
        -17,
        1,
        1.667,
        -17,
        2.567,
        0,
        3.467,
        0
      ]
    },
    {
      "Target": "Parameter",
      "Id": "Param2ship2",
      "Segments": [
        0,
        0,
        2,
        0.2,
        0,
        1,
        0.333,
        0,
        0.467,
        30,
        0.6,
        30,
        1,
        0.944,
        30,
        1.289,
        24.043,
        1.633,
        17,
        1,
        2.244,
        4.505,
        2.856,
        0,
        3.467,
        0
      ]
    },
    {
      "Target": "Parameter",
      "Id": "Param",
      "Segments": [
        0,
        0,
        1,
        0.189,
        0,
        0.378,
        -21,
        0.567,
        -21,
        1,
        0.822,
        -21,
        1.078,
        18,
        1.333,
        18,
        1,
        1.722,
        18,
        2.111,
        -5,
        2.5,
        -5,
        1,
        2.822,
        -5,
        3.145,
        0,
        3.467,
        0
      ]
    },
    {
      "Target": "Parameter",
      "Id": "Param2radar",
      "Segments": [
        0,
        -10,
        1,
        0.544,
        3.333,
        1.089,
        16.667,
        1.633,
        30,
        1,
        1.644,
        10,
        1.656,
        -10,
        1.667,
        -30,
        1,
        2.267,
        -23.333,
        2.867,
        -16.667,
        3.467,
        -10
      ]
    },
    {
      "Target": "Parameter",
      "Id": "ParamiceX",
      "Segments": [
        0,
        0,
        1,
        0.544,
        0,
        1.089,
        29,
        1.633,
        29,
        1,
        2.244,
        29,
        2.856,
        0,
        3.467,
        0
      ]
    },
    {
      "Target": "Parameter",
      "Id": "ParamiceY",
      "Segments": [
        0,
        0,
        1,
        0.544,
        0,
        1.089,
        26,
        1.633,
        26,
        1,
        2.244,
        26,
        2.856,
        0,
        3.467,
        0
      ]
    },
    {
      "Target": "Parameter",
      "Id": "Paramchick11",
      "Segments": [
        0,
        0,
        1,
        0.544,
        0,
        1.089,
        30,
        1.633,
        30,
        1,
        2.244,
        30,
        2.856,
        0,
        3.467,
        0
      ]
    },
    {
      "Target": "Parameter",
      "Id": "Paramchick12eye",
      "Segments": [
        0,
        -30,
        2,
        2.833,
        -30,
        1,
        2.911,
        -30,
        2.989,
        30,
        3.067,
        30,
        1,
        3.122,
        30,
        3.178,
        -30,
        3.233,
        -30,
        2,
        3.467,
        -30
      ]
    },
    {
      "Target": "Parameter",
      "Id": "Param2ChickX",
      "Segments": [
        0,
        0,
        1,
        0.344,
        0,
        0.689,
        -30,
        1.033,
        -30,
        1,
        1.478,
        -30,
        1.922,
        30,
        2.367,
        30,
        1,
        2.734,
        30,
        3.1,
        21.748,
        3.467,
        0
      ]
    },
    {
      "Target": "Parameter",
      "Id": "Paramship1X",
      "Segments": [
        0,
        0,
        1,
        0.467,
        0,
        0.933,
        -13,
        1.4,
        -13,
        1,
        2.089,
        -13,
        2.778,
        0,
        3.467,
        0
      ]
    },
    {
      "Target": "Parameter",
      "Id": "ParamshipY",
      "Segments": [
        0,
        0,
        1,
        0.6,
        0,
        1.2,
        -0.5,
        1.8,
        -0.5,
        1,
        2.356,
        -0.5,
        2.911,
        0,
        3.467,
        0
      ]
    },
    {
      "Target": "Parameter",
      "Id": "ParamchickenblueY",
      "Segments": [
        0,
        0,
        1,
        0.578,
        0,
        1.155,
        12,
        1.733,
        12,
        1,
        2.311,
        12,
        2.889,
        0,
        3.467,
        0
      ]
    },
    {
      "Target": "Parameter",
      "Id": "Paramclogs2X",
      "Segments": [
        0,
        0,
        1,
        0.467,
        0,
        0.933,
        -2,
        1.4,
        -2,
        1,
        2.089,
        -2,
        2.778,
        0,
        3.467,
        0
      ]
    },
    {
      "Target": "Parameter",
      "Id": "Paramclogs2Y",
      "Segments": [
        0,
        0,
        1,
        0.467,
        0,
        0.933,
        -23,
        1.4,
        -23,
        1,
        2.089,
        -23,
        2.778,
        0,
        3.467,
        0
      ]
    },
    {
      "Target": "Parameter",
      "Id": "Paramclogs1Y",
      "Segments": [
        0,
        0,
        1,
        0.544,
        0,
        1.089,
        -12,
        1.633,
        -12,
        1,
        2.244,
        -12,
        2.856,
        0,
        3.467,
        0
      ]
    },
    {
      "Target": "Parameter",
      "Id": "Paramclogs5",
      "Segments": [
        0,
        0,
        1,
        0.467,
        0,
        0.933,
        -20,
        1.4,
        -20,
        1,
        2.089,
        -20,
        2.778,
        0,
        3.467,
        0
      ]
    },
    {
      "Target": "Parameter",
      "Id": "Paramclogs5Y",
      "Segments": [
        0,
        0,
        1,
        0.544,
        0,
        1.089,
        -20,
        1.633,
        -20,
        1,
        2.244,
        -20,
        2.856,
        0,
        3.467,
        0
      ]
    },
    {
      "Target": "Parameter",
      "Id": "ParamthighrX",
      "Segments": [
        0,
        0,
        2,
        0.1,
        0,
        1,
        0.222,
        0,
        0.345,
        -0.037,
        0.467,
        -0.3,
        1,
        0.634,
        -0.659,
        0.8,
        -1,
        0.967,
        -1,
        1,
        1.256,
        -1,
        1.544,
        1,
        1.833,
        1,
        1,
        2.078,
        1,
        2.322,
        0.685,
        2.567,
        0.5,
        1,
        2.867,
        0.273,
        3.167,
        0.132,
        3.467,
        0
      ]
    },
    {
      "Target": "Parameter",
      "Id": "ParamthighRY",
      "Segments": [
        0,
        0,
        2,
        0.133,
        0,
        1,
        0.255,
        0,
        0.378,
        0.016,
        0.5,
        -0.2,
        1,
        0.656,
        -0.474,
        0.811,
        -1,
        0.967,
        -1,
        1,
        1.256,
        -1,
        1.544,
        1,
        1.833,
        1,
        1,
        2.111,
        1,
        2.389,
        0.167,
        2.667,
        0.1,
        1,
        2.934,
        0.036,
        3.2,
        0.067,
        3.467,
        0
      ]
    },
    {
      "Target": "Parameter",
      "Id": "ParamlowerlegRX",
      "Segments": [
        0,
        0,
        2,
        0.2,
        0,
        1,
        0.322,
        0,
        0.445,
        -0.3,
        0.567,
        -0.3,
        1,
        0.7,
        -0.3,
        0.834,
        -0.068,
        0.967,
        0.2,
        1,
        1.256,
        0.781,
        1.544,
        1,
        1.833,
        1,
        1,
        2.133,
        1,
        2.433,
        0.465,
        2.733,
        0.2,
        1,
        2.978,
        -0.016,
        3.222,
        0,
        3.467,
        0
      ]
    },
    {
      "Target": "Parameter",
      "Id": "ParamsoleR",
      "Segments": [
        0,
        0,
        2,
        0.233,
        0,
        1,
        0.355,
        0,
        0.478,
        -0.3,
        0.6,
        -0.3,
        1,
        0.733,
        -0.3,
        0.867,
        0.2,
        1,
        0.2,
        1,
        1.3,
        0.2,
        1.6,
        0.1,
        1.9,
        0.1,
        1,
        2.189,
        0.1,
        2.478,
        0.2,
        2.767,
        0.2,
        1,
        3,
        0.2,
        3.234,
        0,
        3.467,
        0
      ]
    },
    {
      "Target": "Parameter",
      "Id": "Param3YJZ",
      "Segments": [
        0,
        0,
        2,
        0.3,
        0,
        1,
        0.411,
        0,
        0.522,
        15,
        0.633,
        15,
        1,
        0.822,
        15,
        1.011,
        -10,
        1.2,
        -10,
        2,
        2.767,
        -10,
        1,
        3,
        -10,
        3.234,
        0,
        3.467,
        0
      ]
    },
    {
      "Target": "Parameter",
      "Id": "ParamthighlX",
      "Segments": [
        0,
        0,
        2,
        0.067,
        0,
        1,
        0.134,
        0,
        0.2,
        0.4,
        0.267,
        0.4,
        1,
        0.456,
        0.4,
        0.644,
        -0.7,
        0.833,
        -0.7,
        1,
        1.166,
        -0.7,
        1.5,
        -0.448,
        1.833,
        0.2,
        1,
        2.078,
        0.675,
        2.322,
        1,
        2.567,
        1,
        1,
        2.867,
        1,
        3.167,
        0,
        3.467,
        0
      ]
    },
    {
      "Target": "Parameter",
      "Id": "ParamthighY",
      "Segments": [
        0,
        0,
        2,
        0.1,
        0,
        1,
        0.167,
        0,
        0.233,
        -0.4,
        0.3,
        -0.4,
        1,
        0.478,
        -0.4,
        0.655,
        1,
        0.833,
        1,
        1,
        1.189,
        1,
        1.544,
        -1,
        1.9,
        -1,
        2,
        2.6,
        -1,
        1,
        2.889,
        -1,
        3.178,
        0,
        3.467,
        0
      ]
    },
    {
      "Target": "Parameter",
      "Id": "ParamlowerlegLY",
      "Segments": [
        0,
        0,
        2,
        0.267,
        0,
        1,
        0.378,
        0,
        0.489,
        0.1,
        0.6,
        0.1,
        1,
        0.767,
        0.1,
        0.933,
        -0.9,
        1.1,
        -0.9,
        1,
        1.456,
        -0.9,
        1.811,
        -0.854,
        2.167,
        -0.7,
        1,
        2.4,
        -0.599,
        2.634,
        -0.425,
        2.867,
        -0.3,
        1,
        3.067,
        -0.193,
        3.267,
        -0.08,
        3.467,
        0
      ]
    },
    {
      "Target": "Parameter",
      "Id": "ParamlowerleglX",
      "Segments": [
        0,
        0,
        2,
        0.3,
        0,
        1,
        0.411,
        0,
        0.522,
        0.2,
        0.633,
        0.2,
        1,
        0.789,
        0.2,
        0.944,
        -0.586,
        1.1,
        -0.7,
        1,
        1.467,
        -0.969,
        1.833,
        -1,
        2.2,
        -1,
        1,
        2.433,
        -1,
        2.667,
        -0.185,
        2.9,
        -0.1,
        1,
        3.089,
        -0.031,
        3.278,
        -0.055,
        3.467,
        0
      ]
    },
    {
      "Target": "Parameter",
      "Id": "ParamsoleX",
      "Segments": [
        0,
        0,
        2,
        0.833,
        0,
        1,
        1,
        0,
        1.166,
        0.8,
        1.333,
        0.8,
        1,
        1.511,
        0.8,
        1.689,
        0,
        1.867,
        0,
        1,
        2.111,
        0,
        2.356,
        -0.004,
        2.6,
        0.1,
        1,
        2.756,
        0.166,
        2.911,
        0.9,
        3.067,
        0.9,
        1,
        3.2,
        0.9,
        3.334,
        0,
        3.467,
        0
      ]
    },
    {
      "Target": "Parameter",
      "Id": "ParamsolelY",
      "Segments": [
        0,
        0,
        2,
        0.833,
        0,
        1,
        1,
        0,
        1.166,
        1,
        1.333,
        1,
        1,
        1.522,
        1,
        1.711,
        0.964,
        1.9,
        0.4,
        1,
        2.044,
        -0.031,
        2.189,
        -1,
        2.333,
        -1,
        2,
        2.6,
        -1,
        1,
        2.756,
        -1,
        2.911,
        1,
        3.067,
        1,
        1,
        3.2,
        1,
        3.334,
        0.18,
        3.467,
        0
      ]
    },
    {
      "Target": "Parameter",
      "Id": "Paramtoe5",
      "Segments": [
        0,
        0,
        2,
        0.967,
        0,
        1,
        1.245,
        0,
        1.522,
        -0.4,
        1.8,
        -0.4,
        1,
        2.122,
        -0.4,
        2.445,
        0,
        2.767,
        0,
        2,
        3.467,
        0
      ]
    },
    {
      "Target": "Parameter",
      "Id": "Paramtoe4",
      "Segments": [
        0,
        0,
        2,
        0.967,
        0,
        1,
        1.245,
        0,
        1.522,
        0.7,
        1.8,
        0.7,
        1,
        2.122,
        0.7,
        2.445,
        0,
        2.767,
        0,
        2,
        3.467,
        0
      ]
    },
    {
      "Target": "Parameter",
      "Id": "Paramtoe2",
      "Segments": [
        0,
        0,
        2,
        0.967,
        0,
        1,
        1.245,
        0,
        1.522,
        -0.5,
        1.8,
        -0.5,
        1,
        2.122,
        -0.5,
        2.445,
        0,
        2.767,
        0,
        2,
        3.467,
        0
      ]
    },
    {
      "Target": "Parameter",
      "Id": "Paramtoe1",
      "Segments": [
        0,
        0,
        2,
        0.967,
        0,
        1,
        1.245,
        0,
        1.522,
        -1,
        1.8,
        -1,
        1,
        2.122,
        -1,
        2.445,
        0,
        2.767,
        0,
        2,
        3.467,
        0
      ]
    },
    {
      "Target": "Parameter",
      "Id": "ParamUruUruX",
      "Segments": [
        0,
        0,
        1,
        0.122,
        0,
        0.245,
        1,
        0.367,
        1,
        1,
        0.556,
        1,
        0.744,
        0.424,
        0.933,
        0.1,
        1,
        1.355,
        -0.623,
        1.778,
        -0.8,
        2.2,
        -0.8,
        1,
        2.622,
        -0.8,
        3.045,
        0,
        3.467,
        0
      ]
    },
    {
      "Target": "Parameter",
      "Id": "ParamUruUruY",
      "Segments": [
        0,
        0,
        1,
        0.122,
        0,
        0.245,
        1,
        0.367,
        1,
        1,
        0.556,
        1,
        0.744,
        0.36,
        0.933,
        0,
        1,
        1.355,
        -0.804,
        1.778,
        -1,
        2.2,
        -1,
        1,
        2.622,
        -1,
        3.045,
        0,
        3.467,
        0
      ]
    },
    {
      "Target": "Parameter",
      "Id": "ParamEyeBallX",
      "Segments": [
        0,
        0,
        2,
        0.367,
        0,
        1,
        0.5,
        0,
        0.634,
        -0.3,
        0.767,
        -0.3,
        2,
        2.533,
        -0.3,
        1,
        2.844,
        -0.3,
        3.156,
        0,
        3.467,
        0
      ]
    },
    {
      "Target": "Parameter",
      "Id": "ParamEyeBallY",
      "Segments": [
        0,
        0,
        2,
        0.367,
        0,
        1,
        0.5,
        0,
        0.634,
        -0.9,
        0.767,
        -0.9,
        2,
        2.533,
        -0.9,
        1,
        2.844,
        -0.9,
        3.156,
        0,
        3.467,
        0
      ]
    },
    {
      "Target": "Parameter",
      "Id": "ParamEyeROpen",
      "Segments": [
        0,
        1,
        2,
        0.033,
        1,
        1,
        0.178,
        1,
        0.322,
        0,
        0.467,
        0,
        1,
        0.567,
        0,
        0.667,
        1,
        0.767,
        1,
        2,
        1.267,
        1,
        1,
        1.356,
        1,
        1.444,
        0,
        1.533,
        0,
        1,
        1.611,
        0,
        1.689,
        1,
        1.767,
        1,
        2,
        2,
        1,
        1,
        2.067,
        1,
        2.133,
        0,
        2.2,
        0,
        1,
        2.256,
        0,
        2.311,
        1,
        2.367,
        1,
        2,
        3.467,
        1
      ]
    },
    {
      "Target": "Parameter",
      "Id": "ParamEyeLOpen",
      "Segments": [
        0,
        1,
        2,
        0.033,
        1,
        1,
        0.178,
        1,
        0.322,
        0,
        0.467,
        0,
        1,
        0.567,
        0,
        0.667,
        1,
        0.767,
        1,
        2,
        1.267,
        1,
        1,
        1.356,
        1,
        1.444,
        0,
        1.533,
        0,
        1,
        1.611,
        0,
        1.689,
        1,
        1.767,
        1,
        2,
        2,
        1,
        1,
        2.067,
        1,
        2.133,
        0,
        2.2,
        0,
        1,
        2.256,
        0,
        2.311,
        1,
        2.367,
        1,
        2,
        3.467,
        1
      ]
    },
    {
      "Target": "Parameter",
      "Id": "ParamBrowLY",
      "Segments": [
        0,
        0,
        1,
        0.133,
        0,
        0.267,
        -0.9,
        0.4,
        -0.9,
        1,
        0.511,
        -0.9,
        0.622,
        1,
        0.733,
        1,
        1,
        1.644,
        1,
        2.556,
        0,
        3.467,
        0
      ]
    },
    {
      "Target": "Parameter",
      "Id": "ParamBrowRY",
      "Segments": [
        0,
        0,
        1,
        0.133,
        0,
        0.267,
        -0.7,
        0.4,
        -0.7,
        1,
        0.511,
        -0.7,
        0.622,
        1,
        0.733,
        1,
        1,
        1.644,
        1,
        2.556,
        0,
        3.467,
        0
      ]
    },
    {
      "Target": "Parameter",
      "Id": "ParamcoatshakeX",
      "Segments": [
        0,
        -0.2,
        1,
        0.133,
        -0.2,
        0.267,
        -0.009,
        0.4,
        0.1,
        1,
        0.611,
        0.272,
        0.822,
        0.3,
        1.033,
        0.3,
        1,
        1.278,
        0.3,
        1.522,
        -0.5,
        1.767,
        -0.5,
        1,
        2.1,
        -0.5,
        2.434,
        0,
        2.767,
        0,
        1,
        3,
        0,
        3.234,
        -0.2,
        3.467,
        -0.2
      ]
    },
    {
      "Target": "Parameter",
      "Id": "Param3CoatY",
      "Segments": [
        0,
        0,
        1,
        0.133,
        0,
        0.267,
        0.5,
        0.4,
        0.5,
        1,
        0.611,
        0.5,
        0.822,
        -0.7,
        1.033,
        -0.7,
        1,
        1.278,
        -0.7,
        1.522,
        -0.645,
        1.767,
        -0.3,
        1,
        2.1,
        0.171,
        2.434,
        0.6,
        2.767,
        0.6,
        1,
        3,
        0.6,
        3.234,
        0.247,
        3.467,
        0
      ]
    },
    {
      "Target": "Parameter",
      "Id": "Paramhatsribbon1X",
      "Segments": [
        0,
        -1,
        1,
        0.2,
        -1,
        0.4,
        -0.556,
        0.6,
        -0.2,
        1,
        0.956,
        0.433,
        1.311,
        0.6,
        1.667,
        0.6,
        1,
        1.945,
        0.6,
        2.222,
        0.478,
        2.5,
        0,
        1,
        2.822,
        -0.555,
        3.145,
        -1,
        3.467,
        -1
      ]
    },
    {
      "Target": "Parameter",
      "Id": "Paramhatsribbon1Y",
      "Segments": [
        0,
        0,
        1,
        0.2,
        0,
        0.4,
        0.7,
        0.6,
        0.7,
        1,
        0.956,
        0.7,
        1.311,
        0.606,
        1.667,
        0.1,
        1,
        1.945,
        -0.296,
        2.222,
        -0.8,
        2.5,
        -0.8,
        1,
        2.822,
        -0.8,
        3.145,
        -0.52,
        3.467,
        0
      ]
    },
    {
      "Target": "Parameter",
      "Id": "Paramhatsribbon2X",
      "Segments": [
        0,
        0,
        1,
        0.2,
        0,
        0.4,
        0.7,
        0.6,
        0.7,
        1,
        0.956,
        0.7,
        1.311,
        0.509,
        1.667,
        0,
        1,
        1.956,
        -0.414,
        2.244,
        -0.7,
        2.533,
        -0.7,
        1,
        2.844,
        -0.7,
        3.156,
        -0.5,
        3.467,
        0
      ]
    },
    {
      "Target": "Parameter",
      "Id": "Paramhatsribbon2Y",
      "Segments": [
        0,
        0.6,
        1,
        0.2,
        0.6,
        0.4,
        0.384,
        0.6,
        0.1,
        1,
        0.956,
        -0.405,
        1.311,
        -0.6,
        1.667,
        -0.6,
        1,
        1.956,
        -0.6,
        2.244,
        -0.385,
        2.533,
        0,
        1,
        2.844,
        0.414,
        3.156,
        0.6,
        3.467,
        0.6
      ]
    },
    {
      "Target": "Parameter",
      "Id": "Paramwantermelonx",
      "Segments": [
        0,
        0,
        1,
        0.2,
        0,
        0.4,
        -0.6,
        0.6,
        -0.6,
        1,
        0.867,
        -0.6,
        1.133,
        0.6,
        1.4,
        0.6,
        1,
        1.622,
        0.6,
        1.845,
        -0.7,
        2.067,
        -0.7,
        1,
        2.322,
        -0.7,
        2.578,
        0.4,
        2.833,
        0.4,
        1,
        3,
        0.4,
        3.166,
        0.121,
        3.333,
        0,
        1,
        3.378,
        -0.032,
        3.422,
        -0.062,
        3.467,
        -0.089
      ]
    },
    {
      "Target": "Parameter",
      "Id": "Paramwantermelonx2",
      "Segments": [
        0,
        0,
        1,
        0.233,
        0,
        0.467,
        -0.5,
        0.7,
        -0.5,
        1,
        0.978,
        -0.5,
        1.255,
        0.9,
        1.533,
        0.9,
        1,
        1.755,
        0.9,
        1.978,
        -0.8,
        2.2,
        -0.8,
        1,
        2.456,
        -0.8,
        2.711,
        0.4,
        2.967,
        0.4,
        1,
        3.134,
        0.4,
        3.3,
        0.146,
        3.467,
        0
      ]
    },
    {
      "Target": "Parameter",
      "Id": "ParamgarlandX",
      "Segments": [
        0,
        0,
        1,
        0.544,
        0,
        1.089,
        -0.5,
        1.633,
        -0.5,
        1,
        2.244,
        -0.5,
        2.856,
        0,
        3.467,
        0
      ]
    },
    {
      "Target": "Parameter",
      "Id": "ParamsunflowersX",
      "Segments": [
        0,
        0,
        1,
        0.478,
        0,
        0.955,
        -0.5,
        1.433,
        -0.5,
        1,
        2.111,
        -0.5,
        2.789,
        0,
        3.467,
        0
      ]
    },
    {
      "Target": "Parameter",
      "Id": "ParamsunflowerX",
      "Segments": [
        0,
        0,
        1,
        0.578,
        0,
        1.155,
        -1,
        1.733,
        -1,
        1,
        2.311,
        -1,
        2.889,
        0,
        3.467,
        0
      ]
    },
    {
      "Target": "Parameter",
      "Id": "ParamropeX",
      "Segments": [
        0,
        0.5,
        1,
        0.244,
        0.5,
        0.489,
        0.428,
        0.733,
        0.1,
        1,
        1.011,
        -0.272,
        1.289,
        -0.6,
        1.567,
        -0.6,
        1,
        1.878,
        -0.6,
        2.189,
        -0.356,
        2.5,
        0,
        1,
        2.822,
        0.369,
        3.145,
        0.5,
        3.467,
        0.5
      ]
    },
    {
      "Target": "Parameter",
      "Id": "ParamropeY",
      "Segments": [
        0,
        0,
        1,
        0.244,
        0,
        0.489,
        -0.5,
        0.733,
        -0.5,
        1,
        1.011,
        -0.5,
        1.289,
        -0.429,
        1.567,
        -0.1,
        1,
        1.878,
        0.269,
        2.189,
        0.6,
        2.5,
        0.6,
        1,
        2.822,
        0.6,
        3.145,
        0.437,
        3.467,
        0
      ]
    },
    {
      "Target": "Parameter",
      "Id": "ParamarmR",
      "Segments": [
        0,
        0,
        1,
        0.167,
        0,
        0.333,
        -1,
        0.5,
        -1,
        2,
        2.433,
        -1,
        1,
        2.778,
        -1,
        3.122,
        0,
        3.467,
        0
      ]
    },
    {
      "Target": "Parameter",
      "Id": "Paramarm2",
      "Segments": [
        0,
        0,
        1,
        0.144,
        0,
        0.289,
        -0.068,
        0.433,
        -0.1,
        1,
        1.1,
        -0.248,
        1.766,
        -0.336,
        2.433,
        -0.5,
        1,
        2.611,
        -0.544,
        2.789,
        -1,
        2.967,
        -1,
        1,
        3.045,
        -1,
        3.122,
        0,
        3.2,
        0,
        2,
        3.467,
        0
      ]
    },
    {
      "Target": "Parameter",
      "Id": "Paramfinger1r",
      "Segments": [
        0,
        0,
        1,
        0.067,
        0,
        0.133,
        -30,
        0.2,
        -30,
        1,
        1.111,
        -30,
        2.022,
        -29.707,
        2.933,
        -29,
        1,
        2.989,
        -28.957,
        3.044,
        30,
        3.1,
        30,
        1,
        3.222,
        30,
        3.345,
        0,
        3.467,
        0
      ]
    },
    {
      "Target": "Parameter",
      "Id": "Paramfinger2",
      "Segments": [
        0,
        0,
        1,
        0.067,
        0,
        0.133,
        -30,
        0.2,
        -30,
        2,
        2.933,
        -30,
        1,
        2.989,
        -30,
        3.044,
        30,
        3.1,
        30,
        1,
        3.222,
        30,
        3.345,
        0,
        3.467,
        0
      ]
    },
    {
      "Target": "Parameter",
      "Id": "Paramfinger3",
      "Segments": [
        0,
        0,
        1,
        0.067,
        0,
        0.133,
        -30,
        0.2,
        -30,
        2,
        2.933,
        -30,
        1,
        2.989,
        -30,
        3.044,
        30,
        3.1,
        30,
        1,
        3.222,
        30,
        3.345,
        0,
        3.467,
        0
      ]
    },
    {
      "Target": "Parameter",
      "Id": "Paramfinger4",
      "Segments": [
        0,
        0,
        1,
        0.067,
        0,
        0.133,
        -30,
        0.2,
        -30,
        2,
        2.933,
        -30,
        1,
        2.989,
        -30,
        3.044,
        30,
        3.1,
        30,
        1,
        3.222,
        30,
        3.345,
        0,
        3.467,
        0
      ]
    },
    {
      "Target": "Parameter",
      "Id": "Paramfinger5",
      "Segments": [
        0,
        0,
        1,
        0.067,
        0,
        0.133,
        -30,
        0.2,
        -30,
        2,
        2.933,
        -30,
        1,
        2.989,
        -30,
        3.044,
        30,
        3.1,
        30,
        1,
        3.222,
        30,
        3.345,
        0,
        3.467,
        0
      ]
    },
    {
      "Target": "Parameter",
      "Id": "Paramarm2Rx",
      "Segments": [
        0,
        0,
        1,
        0.144,
        0,
        0.289,
        5.827,
        0.433,
        10,
        1,
        0.522,
        12.568,
        0.611,
        13.025,
        0.7,
        15,
        1,
        0.767,
        16.481,
        0.833,
        18,
        0.9,
        18,
        1,
        1.1,
        18,
        1.3,
        11,
        1.5,
        11,
        1,
        1.767,
        11,
        2.033,
        13,
        2.3,
        13,
        1,
        2.367,
        13,
        2.433,
        11,
        2.5,
        11,
        2,
        2.7,
        11,
        1,
        2.733,
        11,
        2.767,
        11.318,
        2.8,
        9,
        1,
        2.844,
        5.91,
        2.889,
        -6,
        2.933,
        -6,
        1,
        3.111,
        -6,
        3.289,
        0,
        3.467,
        0
      ]
    },
    {
      "Target": "Parameter",
      "Id": "Param3A",
      "Segments": [
        0,
        0,
        1,
        0.144,
        0,
        0.289,
        9,
        0.433,
        9,
        2,
        0.5,
        9,
        1,
        0.567,
        9,
        0.633,
        24,
        0.7,
        24,
        2,
        2.5,
        24,
        1,
        2.578,
        24,
        2.655,
        9.845,
        2.733,
        8,
        1,
        2.822,
        5.891,
        2.911,
        6,
        3,
        6,
        2,
        3.467,
        6
      ]
    },
    {
      "Target": "Parameter",
      "Id": "Paramarm1Rd",
      "Segments": [
        0,
        0,
        1,
        0.233,
        0,
        0.467,
        16,
        0.7,
        16,
        2,
        2.5,
        16,
        2,
        2.7,
        16,
        1,
        2.8,
        16,
        2.9,
        30,
        3,
        30,
        1,
        3.156,
        30,
        3.311,
        3.834,
        3.467,
        0
      ]
    },
    {
      "Target": "Parameter",
      "Id": "Paramarm2d",
      "Segments": [
        0,
        30,
        1,
        0.233,
        30,
        0.467,
        -30,
        0.7,
        -30,
        2,
        2.5,
        -30,
        1,
        2.733,
        -30,
        2.967,
        30,
        3.2,
        30,
        2,
        3.467,
        30
      ]
    },
    {
      "Target": "Parameter",
      "Id": "Paramarml1",
      "Segments": [
        0,
        0,
        2,
        0.033,
        0,
        1,
        0.089,
        0,
        0.144,
        0.7,
        0.2,
        0.7,
        1,
        0.333,
        0.7,
        0.467,
        -0.4,
        0.6,
        -0.4,
        1,
        0.933,
        -0.4,
        1.267,
        1,
        1.6,
        1,
        1,
        1.889,
        1,
        2.178,
        -0.2,
        2.467,
        -0.2,
        1,
        2.8,
        -0.2,
        3.134,
        0,
        3.467,
        0
      ]
    },
    {
      "Target": "Parameter",
      "Id": "Paramarml1Y",
      "Segments": [
        0,
        0,
        2,
        0.067,
        0,
        1,
        0.145,
        0,
        0.222,
        -0.6,
        0.3,
        -0.6,
        1,
        0.456,
        -0.6,
        0.611,
        0.3,
        0.767,
        0.3,
        1,
        1.078,
        0.3,
        1.389,
        -1,
        1.7,
        -1,
        1,
        2.011,
        -1,
        2.322,
        0.3,
        2.633,
        0.3,
        1,
        2.911,
        0.3,
        3.189,
        0.275,
        3.467,
        0
      ]
    },
    {
      "Target": "Parameter",
      "Id": "Paramarmxl",
      "Segments": [
        0,
        0,
        2,
        0.133,
        0,
        1,
        0.211,
        0,
        0.289,
        0.257,
        0.367,
        0.3,
        1,
        0.534,
        0.391,
        0.7,
        0.4,
        0.867,
        0.4,
        1,
        1.167,
        0.4,
        1.467,
        0.2,
        1.767,
        0.2,
        1,
        2.089,
        0.2,
        2.411,
        0.4,
        2.733,
        0.4,
        1,
        2.978,
        0.4,
        3.222,
        0,
        3.467,
        0
      ]
    },
    {
      "Target": "Parameter",
      "Id": "ParamarmYL",
      "Segments": [
        0,
        0,
        2,
        0.167,
        0,
        1,
        0.245,
        0,
        0.322,
        -0.7,
        0.4,
        -0.7,
        1,
        0.567,
        -0.7,
        0.733,
        0.7,
        0.9,
        0.7,
        1,
        1.211,
        0.7,
        1.522,
        -0.1,
        1.833,
        -0.1,
        1,
        2.144,
        -0.1,
        2.456,
        0,
        2.767,
        0,
        2,
        3.467,
        0
      ]
    },
    {
      "Target": "Parameter",
      "Id": "Paramhardl",
      "Segments": [
        0,
        0,
        2,
        0.133,
        0,
        1,
        0.2,
        0,
        0.266,
        -0.4,
        0.333,
        -0.4,
        1,
        0.522,
        -0.4,
        0.711,
        0.2,
        0.9,
        0.2,
        1,
        1.189,
        0.2,
        1.478,
        -0.2,
        1.767,
        -0.2,
        1,
        2.1,
        -0.2,
        2.434,
        0.4,
        2.767,
        0.4,
        1,
        3,
        0.4,
        3.234,
        0.179,
        3.467,
        0
      ]
    },
    {
      "Target": "Parameter",
      "Id": "ParambatX",
      "Segments": [
        0,
        0,
        2,
        0.1,
        0,
        1,
        0.211,
        0,
        0.322,
        -0.1,
        0.433,
        -0.1,
        1,
        0.578,
        -0.1,
        0.722,
        0.251,
        0.867,
        0.3,
        1,
        1.145,
        0.395,
        1.422,
        0.4,
        1.7,
        0.4,
        1,
        2.056,
        0.4,
        2.411,
        0.397,
        2.767,
        0.3,
        1,
        3,
        0.237,
        3.234,
        0,
        3.467,
        0
      ]
    },
    {
      "Target": "Parameter",
      "Id": "ParambatY",
      "Segments": [
        0,
        0,
        2,
        0.167,
        0,
        1,
        0.278,
        0,
        0.389,
        -0.1,
        0.5,
        -0.1,
        1,
        0.644,
        -0.1,
        0.789,
        0.3,
        0.933,
        0.3,
        1,
        1.189,
        0.3,
        1.444,
        -1,
        1.7,
        -1,
        1,
        2.078,
        -1,
        2.455,
        0.3,
        2.833,
        0.3,
        1,
        3.044,
        0.3,
        3.256,
        0.099,
        3.467,
        0
      ]
    },
    {
      "Target": "Parameter",
      "Id": "Param3fiy",
      "Segments": [
        0,
        0,
        0,
        3.47,
        0
      ]
    },
    {
      "Target": "Parameter",
      "Id": "ParamCheek",
      "Segments": [
        0,
        0,
        0,
        3.47,
        0
      ]
    },
    {
      "Target": "Parameter",
      "Id": "Param3hats",
      "Segments": [
        0,
        0,
        0,
        3.47,
        0
      ]
    },
    {
      "Target": "Parameter",
      "Id": "ParamBodyAngleY",
      "Segments": [
        0,
        0,
        0,
        3.47,
        0
      ]
    },
    {
      "Target": "Parameter",
      "Id": "Param3body",
      "Segments": [
        0,
        0,
        0,
        3.47,
        0
      ]
    },
    {
      "Target": "Parameter",
      "Id": "Param2mechanics",
      "Segments": [
        0,
        0,
        0,
        3.47,
        0
      ]
    },
    {
      "Target": "Parameter",
      "Id": "Param2MeyeOpen",
      "Segments": [
        0,
        -30,
        0,
        3.47,
        -30
      ]
    },
    {
      "Target": "Parameter",
      "Id": "Param3Meye1",
      "Segments": [
        0,
        -30,
        0,
        3.47,
        -30
      ]
    },
    {
      "Target": "Parameter",
      "Id": "Param2Meye2",
      "Segments": [
        0,
        -30,
        0,
        3.47,
        -30
      ]
    },
    {
      "Target": "Parameter",
      "Id": "Paramice1",
      "Segments": [
        0,
        -30,
        0,
        3.47,
        -30
      ]
    },
    {
      "Target": "Parameter",
      "Id": "Paramchick11X",
      "Segments": [
        0,
        0,
        0,
        3.47,
        0
      ]
    },
    {
      "Target": "Parameter",
      "Id": "Paramchick11Y",
      "Segments": [
        0,
        0,
        0,
        3.47,
        0
      ]
    },
    {
      "Target": "Parameter",
      "Id": "Paramchick1",
      "Segments": [
        0,
        0,
        0,
        3.47,
        0
      ]
    },
    {
      "Target": "Parameter",
      "Id": "Paramchick2",
      "Segments": [
        0,
        0,
        0,
        3.47,
        0
      ]
    },
    {
      "Target": "Parameter",
      "Id": "Paramchick3",
      "Segments": [
        0,
        0,
        0,
        3.47,
        0
      ]
    },
    {
      "Target": "Parameter",
      "Id": "Paramchick4",
      "Segments": [
        0,
        0,
        0,
        3.47,
        0
      ]
    },
    {
      "Target": "Parameter",
      "Id": "ParamshipX",
      "Segments": [
        0,
        0,
        0,
        3.47,
        0
      ]
    },
    {
      "Target": "Parameter",
      "Id": "ParamchickenblueX",
      "Segments": [
        0,
        0,
        0,
        3.47,
        0
      ]
    },
    {
      "Target": "Parameter",
      "Id": "Param3Chicken",
      "Segments": [
        0,
        0,
        0,
        3.47,
        0
      ]
    },
    {
      "Target": "Parameter",
      "Id": "Paramclogs1x",
      "Segments": [
        0,
        0,
        0,
        3.47,
        0
      ]
    },
    {
      "Target": "Parameter",
      "Id": "Paramclogs5X",
      "Segments": [
        0,
        0,
        0,
        3.47,
        0
      ]
    },
    {
      "Target": "Parameter",
      "Id": "Paramtoe1r",
      "Segments": [
        0,
        0,
        0,
        3.47,
        0
      ]
    },
    {
      "Target": "Parameter",
      "Id": "Paramtoe2r",
      "Segments": [
        0,
        0,
        0,
        3.47,
        0
      ]
    },
    {
      "Target": "Parameter",
      "Id": "Paramtoe3r",
      "Segments": [
        0,
        0,
        0,
        3.47,
        0
      ]
    },
    {
      "Target": "Parameter",
      "Id": "Paramtoe4r",
      "Segments": [
        0,
        0,
        0,
        3.47,
        0
      ]
    },
    {
      "Target": "Parameter",
      "Id": "Paramtoe5r",
      "Segments": [
        0,
        0,
        0,
        3.47,
        0
      ]
    },
    {
      "Target": "Parameter",
      "Id": "Param3Toe5_l",
      "Segments": [
        0,
        0,
        0,
        3.47,
        0
      ]
    },
    {
      "Target": "Parameter",
      "Id": "Paramtoe3",
      "Segments": [
        0,
        0,
        0,
        3.47,
        0
      ]
    },
    {
      "Target": "Parameter",
      "Id": "ParamMouthForm",
      "Segments": [
        0,
        -1,
        0,
        3.47,
        -1
      ]
    },
    {
      "Target": "Parameter",
      "Id": "ParamMouthOpenY",
      "Segments": [
        0,
        0,
        0,
        3.47,
        0
      ]
    },
    {
      "Target": "Parameter",
      "Id": "Param2Mouth",
      "Segments": [
        0,
        0,
        0,
        3.47,
        0
      ]
    },
    {
      "Target": "Parameter",
      "Id": "Param2MouthY",
      "Segments": [
        0,
        0,
        0,
        3.47,
        0
      ]
    },
    {
      "Target": "Parameter",
      "Id": "Param2eyeball",
      "Segments": [
        0,
        0,
        0,
        3.47,
        0
      ]
    },
    {
      "Target": "Parameter",
      "Id": "Param2eye",
      "Segments": [
        0,
        0,
        0,
        3.47,
        0
      ]
    },
    {
      "Target": "Parameter",
      "Id": "ParamEyeRSmile",
      "Segments": [
        0,
        0,
        0,
        3.47,
        0
      ]
    },
    {
      "Target": "Parameter",
      "Id": "ParamEyeLSmile",
      "Segments": [
        0,
        0,
        0,
        3.47,
        0
      ]
    },
    {
      "Target": "Parameter",
      "Id": "ParamBrowLX",
      "Segments": [
        0,
        0,
        0,
        3.47,
        0
      ]
    },
    {
      "Target": "Parameter",
      "Id": "ParamBrowRX",
      "Segments": [
        0,
        0,
        0,
        3.47,
        0
      ]
    },
    {
      "Target": "Parameter",
      "Id": "ParamBrowLAngle",
      "Segments": [
        0,
        0,
        0,
        3.47,
        0
      ]
    },
    {
      "Target": "Parameter",
      "Id": "ParamBrowRAngle",
      "Segments": [
        0,
        0,
        0,
        3.47,
        0
      ]
    },
    {
      "Target": "Parameter",
      "Id": "ParamBrowLForm",
      "Segments": [
        0,
        0,
        0,
        3.47,
        0
      ]
    },
    {
      "Target": "Parameter",
      "Id": "ParamBrowRForm",
      "Segments": [
        0,
        0,
        0,
        3.47,
        0
      ]
    },
    {
      "Target": "Parameter",
      "Id": "ParamwatermelonY",
      "Segments": [
        0,
        0,
        0,
        3.47,
        0
      ]
    },
    {
      "Target": "Parameter",
      "Id": "ParamfrenulumX",
      "Segments": [
        0,
        0,
        0,
        3.47,
        0
      ]
    },
    {
      "Target": "Parameter",
      "Id": "ParamhardR",
      "Segments": [
        0,
        0,
        0,
        3.47,
        0
      ]
    },
    {
      "Target": "Parameter",
      "Id": "Param2flash",
      "Segments": [
        0,
        -30,
        0,
        3.47,
        -30
      ]
    },
    {
      "Target": "Parameter",
      "Id": "Param2flash3",
      "Segments": [
        0,
        -30,
        0,
        3.47,
        -30
      ]
    },
    {
      "Target": "Parameter",
      "Id": "Param2flash2",
      "Segments": [
        0,
        -30,
        0,
        3.47,
        -30
      ]
    },
    {
      "Target": "Parameter",
      "Id": "Param2canying",
      "Segments": [
        0,
        -30,
        0,
        3.47,
        -30
      ]
    },
    {
      "Target": "Parameter",
      "Id": "HeadRotat",
      "Segments": [
        0,
        0,
        0,
        3.47,
        0
      ]
    },
    {
      "Target": "PartOpacity",
      "Id": "spray",
      "Segments": [
        0,
        0,
        0,
        3.47,
        0
      ]
    }
  ],
  "UserData": [
    {
      "Time": 2.97,
      "Value": ""
    }
  ]
}