{
  "Version": 3,
  "Meta": {
    "Duration": 6.433,
    "Fps": 30.0,
    "Loop": false,
    "CurveCount": 45,
    "TotalSegmentCount": 332,
    "TotalPointCount": 609,
    "UserDataCount": 1,
    "TotalUserDataSize": 0
  },
  "Curves": [
    {
      "Target": "Parameter",
      "Id": "ParamAngleX",
      "Segments": [
        0,
        0,
        2,
        0.533,
        0,
        1,
        1.022,
        0,
        1.511,
        5,
        2,
        5,
        1,
        2.167,
        5,
        2.333,
        4.598,
        2.5,
        3,
        1,
        2.667,
        1.402,
        2.833,
        0,
        3,
        0,
        2,
        5.333,
        0,
        2,
        5.633,
        0,
        2,
        6.167,
        0,
        2,
        6.4,
        0,
        2,
        6.433,
        0
      ]
    },
    {
      "Target": "Parameter",
      "Id": "ParamAngleY",
      "Segments": [
        0,
        0,
        1,
        0.111,
        0,
        0.222,
        8,
        0.333,
        8,
        2,
        0.533,
        8,
        1,
        1.022,
        8,
        1.511,
        -11,
        2,
        -11,
        1,
        2.167,
        -11,
        2.333,
        -9.987,
        2.5,
        -3,
        1,
        2.667,
        3.987,
        2.833,
        13,
        3,
        13,
        1,
        3.122,
        13,
        3.245,
        -16,
        3.367,
        -16,
        2,
        5.333,
        -16,
        2,
        5.633,
        -16,
        1,
        5.811,
        -16,
        5.989,
        0,
        6.167,
        0,
        2,
        6.4,
        0,
        2,
        6.433,
        0
      ]
    },
    {
      "Target": "Parameter",
      "Id": "ParamAngleZ",
      "Segments": [
        0,
        0,
        2,
        0.533,
        0,
        1,
        0.933,
        0,
        1.333,
        -6,
        1.733,
        -6,
        1,
        1.989,
        -6,
        2.244,
        0,
        2.5,
        0,
        2,
        3,
        0,
        2,
        5.333,
        0,
        2,
        5.633,
        0,
        2,
        6.167,
        0,
        2,
        6.4,
        0,
        2,
        6.433,
        0
      ]
    },
    {
      "Target": "Parameter",
      "Id": "PARAM_eyebrow_Change",
      "Segments": [
        0,
        0,
        2,
        0.533,
        0,
        2,
        2.5,
        0,
        2,
        3,
        0,
        1,
        3.122,
        0,
        3.245,
        1,
        3.367,
        1,
        2,
        5.333,
        1,
        2,
        5.633,
        1,
        1,
        5.811,
        1,
        5.989,
        0,
        6.167,
        0,
        2,
        6.4,
        0,
        2,
        6.433,
        0
      ]
    },
    {
      "Target": "Parameter",
      "Id": "ParamEyeLOpen",
      "Segments": [
        0,
        1,
        2,
        0.533,
        1,
        2,
        1.633,
        1,
        1,
        1.655,
        1,
        1.678,
        0,
        1.7,
        0,
        1,
        1.722,
        0,
        1.745,
        1,
        1.767,
        1,
        2,
        2.5,
        1,
        2,
        3,
        1,
        1,
        3.022,
        1,
        3.045,
        0,
        3.067,
        0,
        1,
        3.089,
        0,
        3.111,
        1,
        3.133,
        1,
        1,
        3.211,
        1,
        3.289,
        0.89,
        3.367,
        0.89,
        2,
        4.167,
        0.89,
        1,
        4.189,
        0.89,
        4.211,
        0,
        4.233,
        0,
        1,
        4.255,
        0,
        4.278,
        0.89,
        4.3,
        0.89,
        1,
        4.322,
        0.89,
        4.345,
        0,
        4.367,
        0,
        1,
        4.389,
        0,
        4.411,
        0.89,
        4.433,
        0.89,
        2,
        5.333,
        0.89,
        1,
        5.433,
        0.89,
        5.533,
        0,
        5.633,
        0,
        1,
        5.733,
        0,
        5.833,
        1,
        5.933,
        1,
        2,
        6.167,
        1,
        2,
        6.4,
        1,
        2,
        6.433,
        1
      ]
    },
    {
      "Target": "Parameter",
      "Id": "ParamEyeROpen",
      "Segments": [
        0,
        1,
        2,
        0.533,
        1,
        2,
        1.633,
        1,
        1,
        1.655,
        1,
        1.678,
        0,
        1.7,
        0,
        1,
        1.722,
        0,
        1.745,
        1,
        1.767,
        1,
        2,
        2.5,
        1,
        2,
        3,
        1,
        1,
        3.022,
        1,
        3.045,
        0,
        3.067,
        0,
        1,
        3.089,
        0,
        3.111,
        1,
        3.133,
        1,
        1,
        3.211,
        1,
        3.289,
        0.89,
        3.367,
        0.89,
        2,
        4.167,
        0.89,
        1,
        4.189,
        0.89,
        4.211,
        0,
        4.233,
        0,
        1,
        4.255,
        0,
        4.278,
        0.89,
        4.3,
        0.89,
        1,
        4.322,
        0.89,
        4.345,
        0,
        4.367,
        0,
        1,
        4.389,
        0,
        4.411,
        0.89,
        4.433,
        0.89,
        2,
        5.333,
        0.89,
        1,
        5.433,
        0.89,
        5.533,
        0,
        5.633,
        0,
        1,
        5.733,
        0,
        5.833,
        1,
        5.933,
        1,
        2,
        6.167,
        1,
        2,
        6.4,
        1,
        2,
        6.433,
        1
      ]
    },
    {
      "Target": "Parameter",
      "Id": "PARAM_Angry_eye",
      "Segments": [
        0,
        0,
        2,
        0.533,
        0,
        2,
        2.5,
        0,
        2,
        3,
        0,
        1,
        3.122,
        0,
        3.245,
        1,
        3.367,
        1,
        2,
        5.333,
        1,
        2,
        5.633,
        1,
        1,
        5.733,
        1,
        5.833,
        0,
        5.933,
        0,
        2,
        6.167,
        0,
        2,
        6.4,
        0,
        2,
        6.433,
        0
      ]
    },
    {
      "Target": "Parameter",
      "Id": "ParamEyeBallX",
      "Segments": [
        0,
        0,
        2,
        0.533,
        0,
        1,
        0.766,
        0,
        1,
        -0.42,
        1.233,
        -0.42,
        1,
        1.366,
        -0.42,
        1.5,
        -0.438,
        1.633,
        -0.34,
        1,
        1.778,
        -0.234,
        1.922,
        0.34,
        2.067,
        0.34,
        1,
        2.211,
        0.34,
        2.356,
        0,
        2.5,
        0,
        2,
        3,
        0,
        2,
        3.367,
        0,
        2,
        5.333,
        0,
        2,
        5.633,
        0,
        2,
        6.167,
        0,
        2,
        6.4,
        0,
        2,
        6.433,
        0
      ]
    },
    {
      "Target": "Parameter",
      "Id": "ParamEyeBallY",
      "Segments": [
        0,
        0,
        2,
        0.533,
        0,
        1,
        0.766,
        0,
        1,
        0.67,
        1.233,
        0.67,
        1,
        1.366,
        0.67,
        1.5,
        -0.58,
        1.633,
        -0.58,
        1,
        1.778,
        -0.58,
        1.922,
        0.38,
        2.067,
        0.38,
        1,
        2.211,
        0.38,
        2.356,
        0,
        2.5,
        0,
        2,
        3,
        0,
        1,
        3.122,
        0,
        3.245,
        0.58,
        3.367,
        0.58,
        2,
        5.333,
        0.58,
        1,
        5.433,
        0.58,
        5.533,
        0,
        5.633,
        0,
        2,
        6.167,
        0,
        2,
        6.4,
        0,
        2,
        6.433,
        0
      ]
    },
    {
      "Target": "Parameter",
      "Id": "ParamMouthForm",
      "Segments": [
        0,
        0,
        1,
        0.111,
        0,
        0.222,
        1,
        0.333,
        1,
        2,
        0.533,
        1,
        2,
        2.5,
        1,
        2,
        3,
        1,
        2,
        5.333,
        1,
        2,
        5.633,
        1,
        1,
        5.733,
        1,
        5.833,
        0,
        5.933,
        0,
        2,
        6.167,
        0,
        2,
        6.4,
        0,
        2,
        6.433,
        0
      ]
    },
    {
      "Target": "Parameter",
      "Id": "ParamMouthOpenY",
      "Segments": [
        0,
        0,
        1,
        0.111,
        0,
        0.222,
        1,
        0.333,
        1,
        2,
        0.533,
        1,
        2,
        2.5,
        1,
        2,
        3,
        1,
        1,
        3.122,
        1,
        3.245,
        0,
        3.367,
        0,
        2,
        5.333,
        0,
        2,
        5.633,
        0,
        1,
        5.733,
        0,
        5.833,
        1,
        5.933,
        1,
        1,
        6.011,
        1,
        6.089,
        0,
        6.167,
        0,
        2,
        6.4,
        0,
        2,
        6.433,
        0
      ]
    },
    {
      "Target": "Parameter",
      "Id": "PARAM_Mouth",
      "Segments": [
        0,
        0,
        1,
        0.111,
        0,
        0.222,
        -1,
        0.333,
        -1,
        2,
        0.533,
        -1,
        2,
        2.5,
        -1,
        2,
        3,
        -1,
        2,
        3.367,
        -1,
        2,
        5.333,
        -1,
        2,
        5.633,
        -1,
        1,
        5.811,
        -1,
        5.989,
        0,
        6.167,
        0,
        2,
        6.4,
        0,
        2,
        6.433,
        0
      ]
    },
    {
      "Target": "Parameter",
      "Id": "PARAM_Mouth_Angle",
      "Segments": [
        0,
        0,
        2,
        0.533,
        0,
        2,
        2.5,
        0,
        2,
        3,
        0,
        1,
        3.122,
        0,
        3.245,
        -1,
        3.367,
        -1,
        2,
        5.333,
        -1,
        2,
        5.633,
        -1,
        1,
        5.811,
        -1,
        5.989,
        0,
        6.167,
        0,
        2,
        6.4,
        0,
        2,
        6.433,
        0
      ]
    },
    {
      "Target": "Parameter",
      "Id": "ParamCheek",
      "Segments": [
        0,
        0.26,
        1,
        0.111,
        0.26,
        0.222,
        1,
        0.333,
        1,
        2,
        0.533,
        1,
        2,
        2.5,
        1,
        2,
        3,
        1,
        2,
        5.333,
        1,
        2,
        5.633,
        1,
        1,
        5.811,
        1,
        5.989,
        0.26,
        6.167,
        0.26,
        2,
        6.4,
        0.26,
        2,
        6.433,
        0.26
      ]
    },
    {
      "Target": "Parameter",
      "Id": "ParamBodyAngleX",
      "Segments": [
        0,
        0,
        2,
        0.533,
        0,
        1,
        0.9,
        0,
        1.266,
        6,
        1.633,
        6,
        1,
        1.922,
        6,
        2.211,
        0,
        2.5,
        0,
        2,
        3,
        0,
        2,
        5.333,
        0,
        2,
        5.633,
        0,
        2,
        6.167,
        0,
        2,
        6.4,
        0,
        2,
        6.433,
        0
      ]
    },
    {
      "Target": "Parameter",
      "Id": "ParamBreath",
      "Segments": [
        0,
        0,
        1,
        0.111,
        0,
        0.222,
        0.74,
        0.333,
        0.74,
        1,
        0.4,
        0.74,
        0.466,
        0.31,
        0.533,
        0.31,
        1,
        0.855,
        0.31,
        1.178,
        0.72,
        1.5,
        0.72,
        1,
        1.833,
        0.72,
        2.167,
        0.2,
        2.5,
        0.2,
        1,
        2.667,
        0.2,
        2.833,
        0.67,
        3,
        0.67,
        1,
        3.122,
        0.67,
        3.245,
        0.17,
        3.367,
        0.17,
        1,
        3.689,
        0.17,
        4.011,
        0.67,
        4.333,
        0.67,
        1,
        4.666,
        0.67,
        5,
        0.513,
        5.333,
        0.17,
        1,
        5.433,
        0.067,
        5.533,
        0,
        5.633,
        0,
        2,
        6.167,
        0,
        2,
        6.4,
        0,
        2,
        6.433,
        0
      ]
    },
    {
      "Target": "Parameter",
      "Id": "PARAM_Arm_LT_Angle",
      "Segments": [
        0,
        0.07,
        2,
        0.533,
        0.07,
        2,
        2.5,
        0.07,
        1,
        2.667,
        0.07,
        2.833,
        1.6,
        3,
        1.6,
        1,
        3.122,
        1.6,
        3.245,
        0,
        3.367,
        0,
        2,
        5.333,
        0,
        2,
        5.633,
        0,
        1,
        5.733,
        0,
        5.833,
        1.5,
        5.933,
        1.5,
        1,
        6.011,
        1.5,
        6.089,
        0.07,
        6.167,
        0.07,
        2,
        6.4,
        0.07,
        2,
        6.433,
        0.07
      ]
    },
    {
      "Target": "Parameter",
      "Id": "PARAM_Arm_RT_Angle",
      "Segments": [
        0,
        0.07,
        2,
        0.533,
        0.07,
        2,
        2.5,
        0.07,
        1,
        2.667,
        0.07,
        2.833,
        1.6,
        3,
        1.6,
        1,
        3.122,
        1.6,
        3.245,
        0,
        3.367,
        0,
        2,
        5.333,
        0,
        2,
        5.633,
        0,
        1,
        5.733,
        0,
        5.833,
        1.5,
        5.933,
        1.5,
        1,
        6.011,
        1.5,
        6.089,
        0.07,
        6.167,
        0.07,
        2,
        6.4,
        0.07,
        2,
        6.433,
        0.07
      ]
    },
    {
      "Target": "Parameter",
      "Id": "PARAM_Arm_LB_Agle",
      "Segments": [
        0,
        0,
        1,
        0.144,
        0,
        0.289,
        0.5,
        0.433,
        0.5,
        2,
        0.533,
        0.5,
        2,
        2.5,
        0.5,
        1,
        2.667,
        0.5,
        2.833,
        0.89,
        3,
        0.89,
        1,
        3.122,
        0.89,
        3.245,
        0,
        3.367,
        0,
        2,
        5.333,
        0,
        2,
        5.633,
        0,
        2,
        6.167,
        0,
        2,
        6.4,
        0,
        2,
        6.433,
        0
      ]
    },
    {
      "Target": "Parameter",
      "Id": "PARAM_Arm_RB_Agle",
      "Segments": [
        0,
        0,
        1,
        0.144,
        0,
        0.289,
        0.66,
        0.433,
        0.66,
        2,
        0.533,
        0.66,
        2,
        2.5,
        0.66,
        1,
        2.667,
        0.66,
        2.833,
        0.89,
        3,
        0.89,
        1,
        3.122,
        0.89,
        3.245,
        0,
        3.367,
        0,
        2,
        5.333,
        0,
        2,
        5.633,
        0,
        2,
        6.167,
        0,
        2,
        6.4,
        0,
        2,
        6.433,
        0
      ]
    },
    {
      "Target": "Parameter",
      "Id": "PARAM_Hand_L1",
      "Segments": [
        0,
        1,
        2,
        0.2,
        1,
        1,
        0.211,
        1,
        0.222,
        0,
        0.233,
        0,
        2,
        0.433,
        0,
        2,
        0.533,
        0,
        2,
        2.5,
        0,
        2,
        3,
        0,
        2,
        5.333,
        0,
        2,
        5.633,
        0,
        2,
        5.867,
        0,
        1,
        5.878,
        0,
        5.889,
        1,
        5.9,
        1,
        2,
        6.167,
        1,
        2,
        6.4,
        1,
        2,
        6.433,
        1
      ]
    },
    {
      "Target": "Parameter",
      "Id": "PARAM_Hand_L3",
      "Segments": [
        0,
        0,
        2,
        0.2,
        0,
        1,
        0.211,
        0,
        0.222,
        1,
        0.233,
        1,
        2,
        0.433,
        1,
        2,
        0.533,
        1,
        2,
        2.5,
        1,
        2,
        3,
        1,
        2,
        5.333,
        1,
        2,
        5.633,
        1,
        2,
        5.867,
        1,
        1,
        5.878,
        1,
        5.889,
        0,
        5.9,
        0,
        2,
        6.167,
        0,
        2,
        6.4,
        0,
        2,
        6.433,
        0
      ]
    },
    {
      "Target": "Parameter",
      "Id": "PARAM_Hand_R1",
      "Segments": [
        0,
        1,
        2,
        0.2,
        1,
        1,
        0.211,
        1,
        0.222,
        0,
        0.233,
        0,
        2,
        0.433,
        0,
        2,
        0.533,
        0,
        2,
        2.5,
        0,
        2,
        3,
        0,
        2,
        5.333,
        0,
        2,
        5.633,
        0,
        2,
        5.867,
        0,
        1,
        5.878,
        0,
        5.889,
        1,
        5.9,
        1,
        2,
        6.167,
        1,
        2,
        6.4,
        1,
        2,
        6.433,
        1
      ]
    },
    {
      "Target": "Parameter",
      "Id": "PARAM_Hand_R3",
      "Segments": [
        0,
        0,
        2,
        0.2,
        0,
        1,
        0.211,
        0,
        0.222,
        1,
        0.233,
        1,
        2,
        0.433,
        1,
        2,
        0.533,
        1,
        2,
        2.5,
        1,
        2,
        3,
        1,
        2,
        5.333,
        1,
        2,
        5.633,
        1,
        2,
        5.867,
        1,
        1,
        5.878,
        1,
        5.889,
        0,
        5.9,
        0,
        2,
        6.167,
        0,
        2,
        6.4,
        0,
        2,
        6.433,
        0
      ]
    },
    {
      "Target": "Parameter",
      "Id": "PARAM_moveY",
      "Segments": [
        0,
        0,
        2,
        0.3,
        0,
        1,
        0.378,
        0,
        0.455,
        -1,
        0.533,
        -1,
        2,
        2.5,
        -1,
        2,
        3,
        -1,
        2,
        5.333,
        -1,
        1,
        5.433,
        -1,
        5.533,
        -1.5,
        5.633,
        -1.5,
        1,
        5.733,
        -1.5,
        5.833,
        0.441,
        5.933,
        0.441,
        1,
        6.011,
        0.441,
        6.089,
        0,
        6.167,
        0,
        2,
        6.4,
        0,
        2,
        6.433,
        0
      ]
    },
    {
      "Target": "Parameter",
      "Id": "PARAM_bodyS",
      "Segments": [
        0,
        0,
        1,
        0.178,
        0,
        0.355,
        -2,
        0.533,
        -2,
        2,
        2.5,
        -2,
        2,
        3,
        -2,
        2,
        5.333,
        -2,
        2,
        5.633,
        -2,
        1,
        5.811,
        -2,
        5.989,
        0,
        6.167,
        0,
        2,
        6.4,
        0,
        2,
        6.433,
        0
      ]
    },
    {
      "Target": "Parameter",
      "Id": "PARAM_gaoguangX",
      "Segments": [
        0,
        0,
        1,
        0.178,
        0,
        0.355,
        -0.18,
        0.533,
        -0.18,
        1,
        0.733,
        -0.18,
        0.933,
        0.06,
        1.133,
        0.06,
        1,
        1.389,
        0.06,
        1.644,
        -0.02,
        1.9,
        -0.02,
        1,
        2.1,
        -0.02,
        2.3,
        0.13,
        2.5,
        0.13,
        1,
        2.667,
        0.13,
        2.833,
        -0.47,
        3,
        -0.47,
        1,
        3.056,
        -0.47,
        3.111,
        -0.01,
        3.167,
        -0.01,
        1,
        3.234,
        -0.01,
        3.3,
        -0.68,
        3.367,
        -0.68,
        1,
        4.022,
        -0.68,
        4.678,
        -0.662,
        5.333,
        -0.59,
        1,
        5.5,
        -0.572,
        5.666,
        -0.468,
        5.833,
        -0.35,
        1,
        6.022,
        -0.216,
        6.211,
        0,
        6.4,
        0,
        2,
        6.433,
        0
      ]
    },
    {
      "Target": "Parameter",
      "Id": "PARAM_gaoguangY",
      "Segments": [
        0,
        0,
        1,
        0.178,
        0,
        0.355,
        0.46,
        0.533,
        0.46,
        1,
        0.733,
        0.46,
        0.933,
        -0.46,
        1.133,
        -0.46,
        2,
        1.9,
        -0.46,
        1,
        2.1,
        -0.46,
        2.3,
        -0.71,
        2.5,
        -0.71,
        1,
        2.667,
        -0.71,
        2.833,
        0.54,
        3,
        0.54,
        1,
        3.056,
        0.54,
        3.111,
        -0.07,
        3.167,
        -0.25,
        1,
        3.234,
        -0.466,
        3.3,
        -0.46,
        3.367,
        -0.46,
        2,
        5.333,
        -0.46,
        1,
        5.5,
        -0.46,
        5.666,
        0.17,
        5.833,
        0.17,
        1,
        6.022,
        0.17,
        6.211,
        0,
        6.4,
        0,
        2,
        6.433,
        0
      ]
    },
    {
      "Target": "Parameter",
      "Id": "ParamBrowLY",
      "Segments": [
        0,
        0,
        0,
        6.433,
        0
      ]
    },
    {
      "Target": "Parameter",
      "Id": "ParamBrowRY",
      "Segments": [
        0,
        0,
        0,
        6.433,
        0
      ]
    },
    {
      "Target": "Parameter",
      "Id": "ParamBrowLX",
      "Segments": [
        0,
        0,
        0,
        6.433,
        0
      ]
    },
    {
      "Target": "Parameter",
      "Id": "ParamBrowRX",
      "Segments": [
        0,
        0,
        0,
        6.433,
        0
      ]
    },
    {
      "Target": "Parameter",
      "Id": "PARAM_Smile_eye",
      "Segments": [
        0,
        0,
        0,
        6.433,
        0
      ]
    },
    {
      "Target": "Parameter",
      "Id": "ParamBodyAngleZ",
      "Segments": [
        0,
        0,
        0,
        6.433,
        0
      ]
    },
    {
      "Target": "Parameter",
      "Id": "PARAM_Arm_L_hand",
      "Segments": [
        0,
        0,
        0,
        6.433,
        0
      ]
    },
    {
      "Target": "Parameter",
      "Id": "PARAM_Arm_R_hand",
      "Segments": [
        0,
        0,
        0,
        6.433,
        0
      ]
    },
    {
      "Target": "Parameter",
      "Id": "PARAM_Hairfront_vive",
      "Segments": [
        0,
        0,
        0,
        6.433,
        0
      ]
    },
    {
      "Target": "Parameter",
      "Id": "PARAM_Hand_L2",
      "Segments": [
        0,
        0,
        0,
        6.433,
        0
      ]
    },
    {
      "Target": "Parameter",
      "Id": "ParamHl4",
      "Segments": [
        0,
        0,
        0,
        6.433,
        0
      ]
    },
    {
      "Target": "Parameter",
      "Id": "PARAM_Hand_R2",
      "Segments": [
        0,
        0,
        0,
        6.433,
        0
      ]
    },
    {
      "Target": "Parameter",
      "Id": "ParamHr4",
      "Segments": [
        0,
        0,
        0,
        6.433,
        0
      ]
    },
    {
      "Target": "Parameter",
      "Id": "PARAM_mouth",
      "Segments": [
        0,
        1,
        0,
        6.433,
        1
      ]
    },
    {
      "Target": "Parameter",
      "Id": "PARAM_moveX",
      "Segments": [
        0,
        0,
        0,
        6.433,
        0
      ]
    },
    {
      "Target": "Parameter",
      "Id": "PARAM_ruyao",
      "Segments": [
        0,
        0,
        0,
        6.433,
        0
      ]
    },
    {
      "Target": "Parameter",
      "Id": "PARAM_hand_FX",
      "Segments": [
        0,
        -1,
        0,
        6.433,
        -1
      ]
    }
  ],
  "UserData": [
    {
      "Time": 6.433,
      "Value": ""
    }
  ]
}